energyplus_wrapper/__init__.py
energyplus_wrapper/env_manager.py
energyplus_wrapper/runner.py
energyplus_wrapper/simulation.py
energyplus_wrapper/utils.py
energyplus_wrapper-2.0.0.dist-info/METADATA
energyplus_wrapper-2.0.0.dist-info/WHEEL
energyplus_wrapper-2.0.0.dist-info/licenses/LICENSE
energyplus_wrapper-2.0.0.dist-info/RECORD
