Metadata-Version: 2.4
Name: energyplus-wrapper
Version: 2.0.0
Summary: A wrapper for EnergyPlus
License-File: LICENSE
Requires-Python: >=3.10
Requires-Dist: beautifulsoup4<=4.8.0
Requires-Dist: coolname>=2.2.0
Requires-Dist: eppy>=0.5.63
Requires-Dist: fasteners>=0.19
Requires-Dist: joblib>=1.4.2
Requires-Dist: loguru>=0.7.3
Requires-Dist: pandas>=2.2.3
Requires-Dist: pexpect>=4.9.0
Requires-Dist: platformdirs>=4.3.6
Requires-Dist: plumbum>=1.9.0
Requires-Dist: python-box>=7.3.2
Requires-Dist: python-slugify>=8.0.4
Requires-Dist: requests>=2.32.3
